kcode/__init__.py
kcode/utils/__init__.py
kcode/utils/pid.py
kcode-1.0.0.dist-info/LICENSE
kcode-1.0.0.dist-info/METADATA
kcode-1.0.0.dist-info/WHEEL
kcode-1.0.0.dist-info/top_level.txt
kcode-1.0.0.dist-info/RECORD
