Metadata-Version: 2.1
Name: kcode
Version: 1.0.0
Summary: King-code package
Home-page: https://github.com/frolpaxa/kcode
Author: Pavel Frolov
Author-email: pfrol007@gmail.com
Classifier: Programming Language :: Python :: 3
Classifier: License :: OSI Approved :: MIT License
Classifier: Operating System :: OS Independent
Requires-Python: >=3.6
License-File: LICENSE
